kroger_mcp/__init__.py
kroger_mcp/cli.py
kroger_mcp/prompts.py
kroger_mcp/server.py
kroger_mcp/tools/__init__.py
kroger_mcp/tools/auth.py
kroger_mcp/tools/auth_tools.py
kroger_mcp/tools/cart_tools.py
kroger_mcp/tools/info_tools.py
kroger_mcp/tools/location_tools.py
kroger_mcp/tools/product_tools.py
kroger_mcp/tools/profile_tools.py
kroger_mcp/tools/shared.py
kroger_mcp/tools/utility_tools.py
kroger_mcp-0.2.0.dist-info/METADATA
kroger_mcp-0.2.0.dist-info/WHEEL
kroger_mcp-0.2.0.dist-info/entry_points.txt
kroger_mcp-0.2.0.dist-info/licenses/LICENSE
kroger_mcp-0.2.0.dist-info/RECORD
