Metadata-Version: 2.4
Name: kroger-mcp
Version: 0.2.0
Summary: FastMCP server for Kroger API integration
Project-URL: Homepage, https://github.com/CupOfOwls/kroger-mcp
Project-URL: Repository, https://github.com/CupOfOwls/kroger-mcp
Project-URL: Issues, https://github.com/CupOfOwls/kroger-mcp/issues
Project-URL: Kroger_Documentation, https://developer.kroger.com/documentation/public/
Author-email: Stephen Thoemmes <thoemmes.stephen@gmail.com>
License: MIT License
License-File: LICENSE
Keywords: grocery,kroger,mcp,retail,shopping
Classifier: Development Status :: 4 - Beta
Classifier: Intended Audience :: Developers
Classifier: License :: OSI Approved :: MIT License
Classifier: Programming Language :: Python :: 3
Classifier: Programming Language :: Python :: 3.10
Classifier: Programming Language :: Python :: 3.11
Classifier: Programming Language :: Python :: 3.12
Classifier: Topic :: Internet :: WWW/HTTP :: Dynamic Content
Classifier: Topic :: Office/Business
Classifier: Topic :: Software Development :: Libraries :: Python Modules
Requires-Python: >=3.10
Requires-Dist: fastmcp>=2.0.0
Requires-Dist: kroger-api>=0.2.0
Requires-Dist: pydantic>=2.0.0
Requires-Dist: python-dotenv
Requires-Dist: requests
Provides-Extra: dev
Requires-Dist: black; extra == 'dev'
Requires-Dist: pytest; extra == 'dev'
Requires-Dist: pytest-asyncio; extra == 'dev'
Requires-Dist: ruff; extra == 'dev'
